<?xml version="1.0" encoding="UTF-8"?>
<!DOCTYPE filesystem PUBLIC "-//NetBeans//DTD Filesystem 1.2//EN" "http://www.netbeans.org/dtds/filesystem-1_2.dtd">
<filesystem>
    <folder name="Toolbars">
        <folder name="QuickSearch"> 
            <file name="org-netbeans-modules-quicksearch-QuickSearchAction.shadow"> 
                <attr name="originalFile" stringvalue="Actions/Edit/org-netbeans-modules-quicksearch-QuickSearchAction.instance"/>
            </file>
        </folder>
    </folder>
    <folder name="Menu">
        <folder name="Actions">
            <folder name="Ontology">
                <attr name="position" intvalue="600"/>
            </folder>
        </folder>
    </folder>
</filesystem>
