<ehcache 
    xsi:noNamespaceSchemaLocation="ehcache.xsd"
    updateCheck="false"
    monitoring="off" 
    dynamicConfig="false">
    <!-- maxBytesLocalDisk="0g"    -->
    <transactionManagerLookup class="net.sf.ehcache.transaction.manager.DefaultTransactionManagerLookup" properties="jndiName=java:/TransactionManager" propertySeparator=";"/>
    <cacheManagerEventListenerFactory class="" properties=""/>
    <defaultCache maxEntriesLocalHeap="0" eternal="false" timeToIdleSeconds="0" timeToLiveSeconds="0">
    </defaultCache>
    <sizeOfPolicy maxDepth="10000" maxDepthExceededBehavior="continue"/>
    <cache name="CompressedTiffCache"
           timeToIdleSeconds="0" 
           timeToLiveSeconds="0" 
           memoryStoreEvictionPolicy="LRU"
           eternal="true"
           overflowToOffHeap="false"
           maxBytesLocalHeap="16G"
    >
        <!--transactionalMode="off"-->
        <!-- maxEntriesLocalHeap="0"
             maxEntriesLocalDisk="0" 
             diskSpoolBufferSizeMB="0" -->
        <!-- No disk storage is needed. -->
        <!--<persistence strategy="localTempSwap"/>-->
        <!--<pinning store="localHeap"/>-->
    </cache>
</ehcache>
